<annotation>
	<folder>kimchi</folder>
	<filename>IMG_8058.jpeg</filename>
	<path>/Users/jinwonchoi/Downloads/kimchi/IMG_8058.jpeg</path>
	<source>
		<database>Unknown</database>
	</source>
	<size>
		<width>3024</width>
		<height>4032</height>
		<depth>3</depth>
	</size>
	<segmented>0</segmented>
	<object>
		<name>kimchi</name>
		<pose>Unspecified</pose>
		<truncated>0</truncated>
		<difficult>0</difficult>
		<bndbox>
			<xmin>782</xmin>
			<ymin>1391</ymin>
			<xmax>1782</xmax>
			<ymax>2551</ymax>
		</bndbox>
	</object>
</annotation>
